craftapi/__init__.py
craftapi/nytgames.py
craftapi/requests.py
craftapi/vartools.py
craftllc_api-0.1.3.dist-info/METADATA
craftllc_api-0.1.3.dist-info/WHEEL
craftllc_api-0.1.3.dist-info/top_level.txt
craftllc_api-0.1.3.dist-info/RECORD
