Metadata-Version: 2.4
Name: craftllc-api
Version: 0.1.3
Summary: CraftAPI, easy to use scraping and API library.
Author-email: CraftLLC <craftllcompany@gmail.com>
License: MIT
Keywords: api,craftapi,craftllc,craftllc-api
Classifier: Programming Language :: Python :: 3
Classifier: License :: OSI Approved :: MIT License
Classifier: Operating System :: OS Independent
Requires-Dist: requests
Requires-Dist: bs4
